{"cameraMode":{"drawMode":0,"name":"Shaded","section":"Shading Mode"},"sceneLighting":false,"audioPlay":false,"sceneViewState":{"m_AlwaysRefresh":false,"showFog":false,"showSkybox":false,"showFlares":false,"showImageEffects":false,"showParticleSystems":false,"showVisualEffectGraphs":true,"m_FxEnabled":true},"in2DMode":false,"pivot":{"x":-1.3125536441802979,"y":1.0268478393554688,"z":-0.7810524702072144},"rotation":{"x":0.041374705731868747,"y":-0.9441848993301392,"z":0.127830371260643,"w":0.30214983224868777},"size":1.8247500658035279,"orthographic":false}